{"url": "http://www.eia.gov/cfapps/ipdbproject/IEDIndex3.cfm?tid=50&pid=53&aid=1", "text": "Projects published on Beta are not final and may contain programming errors. They are for public testing and comment only. We welcome your feedback. For final products, please visit www.eia.gov.", "images": ["http://www.eia.gov/global/images/logos/eia_logo_print.png", "http://www.eia.gov/favicon.ico"], "top_img": "http://www.eia.gov/favicon.ico", "keywords": [], "authors": [], "canonical_link": "", "title": "International Energy Statistics", "meta_data": {"robots": "all", "agency": "EIA - Energy Information Administration", "subject": "official energy statistics, data, analysis and forecasting", "Description": "Energy Information Administration - EIA - Official Energy Statistics from the U.S. Government"}, "movies": [], "publish_date": null, "source": "http://www.eia.gov", "summary": ""}